pycounts_gcoronel/__init__.py
pycounts_gcoronel/plotting.py
pycounts_gcoronel/pycounts_gcoronel.py
pycounts_gcoronel-0.1.0.dist-info/LICENSE
pycounts_gcoronel-0.1.0.dist-info/WHEEL
pycounts_gcoronel-0.1.0.dist-info/METADATA
pycounts_gcoronel-0.1.0.dist-info/RECORD
