Metadata-Version: 2.1
Name: pycounts-gcoronel
Version: 0.1.0
Summary: Calculate word counts in a text file as described in the Python Packages book!
License: MIT
Author: Gabriel Coronel
Requires-Python: >=3.9
Classifier: License :: OSI Approved :: MIT License
Classifier: Programming Language :: Python :: 3
Classifier: Programming Language :: Python :: 3.9
Classifier: Programming Language :: Python :: 3.10
Classifier: Programming Language :: Python :: 3.11
Requires-Dist: matplotlib (>=3.6.3)
